{"type":"PR","pr":{"number":39,"head":"3afbd0524756bdff93c8949ae9aa90680b8f2040"},"user":"luke","status":"pending_publish","branch":"cms/5071","collection":"special","title":"No Title","description":"No Description!","objects":{"entry":{"path":"content/specials/5071.md","sha":"218902bfd258473bbaa3c909fc534e8763bcab87"},"files":[{"path":"/static/assets/5071.jpg","sha":"fc3f405983c13b174558aef830ab0b2bd0e424e6"},{"path":"/static/assets/5071-2.jpg","sha":"9a16d880ab02e519e5cf4b42342d2593b51102ac"}]},"timeStamp":"2019-04-08T18:37:38.868Z"}